vcmp/__init__.py
vcmp/__init__.pyi
vcmp/callback.py
vcmp/callback.pyi
vcmp/instance.py
vcmp/instance.pyi
vcmp/pool.py
vcmp/pool.pyi
vcmp/streams.py
vcmp/streams.pyi
vcmp/types.py
vcmp/types.pyi
vcmp/util.py
vcmp/util.pyi
vcmp/events/__init__.py
vcmp/events/__init__.pyi
vcmp/events/abc.py
vcmp/events/abc.pyi
vcmp/events/checkpoint.py
vcmp/events/checkpoint.pyi
vcmp/events/custom.py
vcmp/events/custom.pyi
vcmp/events/object.py
vcmp/events/object.pyi
vcmp/events/pickup.py
vcmp/events/pickup.pyi
vcmp/events/player.py
vcmp/events/player.pyi
vcmp/events/server.py
vcmp/events/server.pyi
vcmp/events/vehicle.py
vcmp/events/vehicle.pyi
vcmp/extend/stream.nut
vcmp/functions/__init__.py
vcmp/functions/__init__.pyi
vcmp/functions/checkpoint.py
vcmp/functions/checkpoint.pyi
vcmp/functions/environment.py
vcmp/functions/environment.pyi
vcmp/functions/keybind.py
vcmp/functions/keybind.pyi
vcmp/functions/marker.py
vcmp/functions/marker.pyi
vcmp/functions/misc.py
vcmp/functions/misc.pyi
vcmp/functions/object.py
vcmp/functions/object.pyi
vcmp/functions/pickup.py
vcmp/functions/pickup.pyi
vcmp/functions/player.py
vcmp/functions/player.pyi
vcmp/functions/server.py
vcmp/functions/server.pyi
vcmp/functions/vehicle.py
vcmp/functions/vehicle.pyi
vcmp/libraries/python04rel64rspyo3py310.dll
vcmp/libraries/python04rel64rspyo3py310.so
vcmp/libraries/python04rel64rspyo3py311.dll
vcmp/libraries/python04rel64rspyo3py311.so
vcmp/libraries/python04rel64rspyo3py312.dll
vcmp/libraries/python04rel64rspyo3py312.so
vcmp/libraries/python04rel64rspyo3py313.dll
vcmp/libraries/python04rel64rspyo3py313.so
vcmp_python_plugin-2.1.2.dist-info/licenses/LICENSE
vcmp_python_plugin-2.1.2.dist-info/METADATA
vcmp_python_plugin-2.1.2.dist-info/WHEEL
vcmp_python_plugin-2.1.2.dist-info/top_level.txt
vcmp_python_plugin-2.1.2.dist-info/RECORD
