Metadata-Version: 2.4
Name: vcmp-python-plugin
Version: 2.1.2
Summary: Python for VC:MP Server Plugin
Author-email: tianxiu2b2t <atianxiua@163.com>, shenjack <3695888@qq.com>
License: MIT
Project-URL: homepage, https://github.com/tianxiu2b2t/vcmp-python-plugin
Project-URL: repository, https://github.com/tianxiu2b2t/vcmp-python-plugin
Requires-Python: >=3.10
License-File: LICENSE
Dynamic: license-file
